{
  "basePrice": 750000.0,
  "groupID": 163,
  "iconID": 20954,
  "marketGroupID": 1543,
  "name": {
    "de": "Thermal Energized Membrane I Blueprint",
    "en": "Thermal Energized Membrane I Blueprint",
    "es": "Plano de membrana energizada térmica I",
    "fr": "Plan de construction Membrane énergétique thermique I",
    "ja": "サーマル電磁加工装甲I設計図",
    "ko": "열 저항력 에너지 멤브레인 I 블루프린트",
    "ru": "Thermal Energized Membrane I Blueprint",
    "zh": "热能电压薄膜蓝图 I"
  },
  "portionSize": 1,
  "published": true,
  "volume": 0.01
}