{
  "description": {
    "de": "Dies ist die \"Jungfrau in Nöten\".",
    "en": "This is the damsel in distress.",
    "es": "Esta es la damisela en apuros.",
    "fr": "Il s'agit de la damoiselle en détresse.",
    "ja": "助けを求めている女性。",
    "ko": "위기에 처한 소녀입니다.",
    "ru": "Это девица в беде.",
    "zh": "这是处于危难中的少女。"
  },
  "groupID": 283,
  "iconID": 2537,
  "mass": 60.0,
  "name": {
    "de": "The Damsel",
    "en": "The Damsel",
    "es": "La Damisela",
    "fr": "La damoiselle",
    "ja": "ダムセル",
    "ko": "소녀",
    "ru": "The Damsel",
    "zh": "少女"
  },
  "portionSize": 1,
  "published": true,
  "volume": 0.1
}