{
  "description": {
    "de": "Erhöht die Stromnetzleistung.",
    "en": "Boosts power core output.",
    "es": "Aumenta el rendimiento del núcleo de potencia.",
    "fr": "Améliore la puissance d'alimentation du réacteur principal.",
    "ja": "パワーコアの出力を向上させる。",
    "ko": "파워그리드 용량이 증가합니다.",
    "ru": "Увеличивает производительность энергосистемы корабля.",
    "zh": "提升能源核心输出功率。"
  },
  "groupID": 769,
  "iconID": 26547,
  "marketGroupID": 659,
  "mass": 20.0,
  "metaGroupID": 2,
  "name": {
    "de": "Reactor Control Unit II",
    "en": "Reactor Control Unit II",
    "es": "Unidad de control de reactor II",
    "fr": "Unité de contrôle du réacteur II",
    "ja": "リアクター制御装置II",
    "ko": "반응로 제어유닛 II",
    "ru": "Reactor Control Unit II",
    "zh": "反应堆控制元件 II"
  },
  "portionSize": 1,
  "published": true,
  "radius": 500.0,
  "variationParentTypeID": 1353,
  "volume": 5.0
}