{
  "basePrice": 70258.0,
  "capacity": 128.0,
  "description": {
    "de": "Bewirkt eine Soforteinspeisung von Energie in den Energiespeicher.",
    "en": "Provides a quick injection of power into the capacitor.",
    "es": "Inyectan rápidamente potencia en el condensador.",
    "fr": "Permet de faire bénéficier le capaciteur d'un surcroît de puissance temporaire.",
    "ja": "キャパシタを急速充電することができる。",
    "ko": "캐패시터에 추가 전력을 주입합니다.",
    "ru": "Обеспечивает быстрое повышение мощности конденсатора.",
    "zh": "向电容提供快速能量注入。"
  },
  "groupID": 76,
  "iconID": 1031,
  "marketGroupID": 701,
  "metaGroupID": 4,
  "name": {
    "de": "Ammatar Navy Heavy Capacitor Booster",
    "en": "Ammatar Navy Heavy Capacitor Booster",
    "es": "Potenciador de condensador pesado de la Armada Ammatar",
    "fr": "Booster de capaciteur lourd de l'Ammatar Navy",
    "ja": "アマター海軍仕様大型キャパシタブースター",
    "ko": "아마타 해군 대형 캐패시터 부스터",
    "ru": "Ammatar Navy Heavy Capacitor Booster",
    "zh": "艾玛达海军重型电容注电器"
  },
  "portionSize": 1,
  "published": true,
  "variationParentTypeID": 3576,
  "volume": 20.0
}