{
  "basePrice": 230.0,
  "description": {
    "de": "Fulleride sind hochgradig supraleitende Materialien, die in Energiespeichern, Panzerungen und Waffensystemen Verwendung finden.",
    "en": "Fullerides are highly superconductive materials used in capacitors, armor plating and weapons systems.",
    "es": "Los fuléridos son materiales superconductores que se usan en condensadores, blindajes y sistemas de armas.",
    "fr": "Les fullerides sont des matériaux hautement supraconducteurs utilisés dans les capaciteurs, le revêtement de blindage et les systèmes d'armement.",
    "ja": "キャパシタ、アーマープレート、兵器システムに使用される、高い超伝導性を持つ素材。",
    "ko": "퓰러라이드는 초전도성 물질로 캐패시터, 장갑 플레이팅, 그리고 무기 시스템 제작에 사용됩니다.",
    "ru": "Фуллериды - высокопроводниковые материалы, используемые в конденсаторах, бронированной обшивке и системах оружия.",
    "zh": "富勒化合物是用于电容器、装甲附甲和武器系统中的一种超导材料。"
  },
  "groupID": 429,
  "iconID": 2684,
  "marketGroupID": 499,
  "name": {
    "de": "Fullerides",
    "en": "Fullerides",
    "es": "Fuléridos",
    "fr": "Fullerides",
    "ja": "フラライド",
    "ko": "풀러라이드",
    "ru": "Fullerides",
    "zh": "富勒化合物"
  },
  "portionSize": 1,
  "published": true,
  "volume": 0.15
}