{
  "capacity": 125.0,
  "description": {
    "de": "Eine Elitefregatte des Staates Caldari.",
    "en": "An elite frigate of the Caldari State.",
    "es": "Una fragata de élite del Estado Caldari.",
    "fr": "Une frégate d'élite de l'État caldari.",
    "ja": "カルダリ連合のエリートフリゲート。",
    "ko": "칼다리 연합의 엘리트 프리깃입니다.",
    "ru": "Усовершенствованный фрегат Государства Caldari.",
    "zh": "加达里合众国的精英护卫舰。"
  },
  "graphicID": 1792,
  "groupID": 671,
  "mass": 1970000.0,
  "name": {
    "de": "Taibu State Shirasaya",
    "en": "Taibu State Shirasaya",
    "es": "Shirasaya taibu del Estado",
    "fr": "Taibu Shirasaya de l'État",
    "ja": "タイブ連合軍艦シラサヤ",
    "ko": "칼다리 타이푸 시라사야",
    "ru": "Taibu State Shirasaya",
    "zh": "合众国死士希洛萨"
  },
  "portionSize": 1,
  "published": false,
  "raceID": 1,
  "radius": 50.0,
  "sofFactionName": "caldarinavy",
  "volume": 19700.0
}