{
  "description": {
    "de": "Ein Wissenschaftler, spezialisiert auf den Bau von Drohnen und die Programmierung künstlicher Intelligenz.",
    "en": "A scientist specialized in Drone Creation and AI programming.",
    "es": "Un científico especializado en la creación de drones y la programación de IA.",
    "fr": "Scientifique spécialisé dans la création de drones et la programmation d'intelligence artificielle.",
    "ja": "ドローン製作とAIプログラミングを得意とする科学者。",
    "ko": "드론 제작 및 인공지능에 특화된 과학자입니다.",
    "ru": "Ученый, специализирующийся на разработке дронов и программировании искусственного интеллекта.",
    "zh": "一个无人机生产和编程方面的专家。"
  },
  "groupID": 283,
  "iconID": 2891,
  "mass": 80.0,
  "name": {
    "de": "Lazron Kamon",
    "en": "Lazron Kamon",
    "es": "Lazron Kamon",
    "fr": "Lazron Kamon",
    "ja": "ラズロンカモン",
    "ko": "라즈론 카몬",
    "ru": "Lazron Kamon",
    "zh": "拉扎·卡蒙"
  },
  "portionSize": 1,
  "published": true,
  "volume": 3.0
}