{
  "description": {
    "de": "Die Nichte eines minmatarischen Erntearbeiters, der in 760-9C arbeitet.",
    "en": "The niece of a Minmatar harvester working in 760-9C.",
    "es": "La sobrina de un cosechador minmatariano que trabajó en el periodo 760-9 C.",
    "fr": "Nièce d'un collecteur minmatar travaillant dans la constellation 760-9C.",
    "ja": "760-9Cで作業に当たっている、ミンマター採掘者の姪。",
    "ko": "760-9C에서 일하고 있는 민마타 하베스터의 조카입니다.",
    "ru": "Племянница сборщика Minmatar, работающего в 760-9С.",
    "zh": "一个在760-9C工作的米玛塔尔矿工的侄女。"
  },
  "groupID": 283,
  "iconID": 2537,
  "mass": 60.0,
  "name": {
    "de": "Sidura Meisana",
    "en": "Sidura Meisana",
    "es": "Sidura Meisana",
    "fr": "Sidura Meisana",
    "ja": "シドゥラメイサナ",
    "ko": "시두라 메이사나",
    "ru": "Sidura Meisana",
    "zh": "塞杜拉·梅萨纳"
  },
  "portionSize": 1,
  "published": true,
  "volume": 0.1
}