{
  "graphicID": 3298,
  "groupID": 841,
  "iconID": 21,
  "metaGroupID": 4,
  "name": {
    "de": "Shadow Control Tower Small Blueprint",
    "en": "Shadow Control Tower Small Blueprint",
    "es": "Plano de torre de control pequeña de la Sombra",
    "fr": "Plan de construction Petite tour de contrôle shadow",
    "ja": "シャドウ小型コントロールタワーブループリント",
    "ko": "섀도우 소형 관제타워 블루프린트",
    "ru": "Shadow Control Tower Small Blueprint",
    "zh": "暗影小型控制塔蓝图"
  },
  "portionSize": 1,
  "published": true,
  "sofFactionName": "serpentis",
  "volume": 0.01
}