{
  "description": {
    "de": "Eine komplexe, chemische Formel zur Anwendung bei einer traditionellen Zeremonie der Minmatar. Diese Ladung ist mit einer Markierung der Amarr gekennzeichnet.",
    "en": "A complex chemical formula for use in a traditional Minmatar ceremony. This batch is labeled with Amarr markings.",
    "es": "Una compleja fórmula química que se usa en una ceremonia minmatariana tradicional. Este lote está etiquetado con marcas amarrianas.",
    "fr": "Formule chimique complexe utilisée par les cérémonies minmatar. Cet échantillon présente la marque des Amarr.",
    "ja": "ミンマターの伝統的な儀式で使用する合成化学物質。アマーのマークが付いている。",
    "ko": "민마타 전통 의식에 사용되는 화학 물질입니다. 보관 용기에 아마르 제국의 문장이 새겨져 있습니다.",
    "ru": "Сложный химический состав, использующийся в традиционной церемонии Minmatar. Эта партия несет маркировку Amarr.",
    "zh": "这是一种用于米玛塔尔传统庆祝仪式的复杂的化学配方。这批产品的标签上带有艾玛标记。"
  },
  "groupID": 314,
  "iconID": 1207,
  "mass": 20.0,
  "name": {
    "de": "Counterfeit Voluval Tattoo Chemicals",
    "en": "Counterfeit Voluval Tattoo Chemicals",
    "es": "Químicos para tatuajes de Voluval falsificados",
    "fr": "Produit de tatouage Voluval contrefait",
    "ja": "模造ボリュバルタトゥー化学物質",
    "ko": "가짜 보루발 문신 약품",
    "ru": "Counterfeit Voluval Tattoo Chemicals",
    "zh": "假冒的沃鲁瓦图腾配方"
  },
  "portionSize": 1,
  "published": true,
  "volume": 20.0
}