{
  "description": {
    "de": "Eine Mauer.",
    "en": "A wall.",
    "es": "Un muro.",
    "fr": "Mur.",
    "ja": "壁。",
    "ko": "벽입니다.",
    "ru": "Стена.",
    "zh": "壁垒"
  },
  "graphicID": 2588,
  "groupID": 226,
  "name": {
    "de": "Fortified Drone Wall",
    "en": "Fortified Drone Wall",
    "es": "Muro de drones fortificado",
    "fr": "Mur de drone renforcé",
    "ja": "守りの堅いドローンの壁",
    "ko": "요새화된 드론 외벽",
    "ru": "Fortified Drone Wall",
    "zh": "强化的无人机之墙"
  },
  "portionSize": 1,
  "published": false,
  "raceID": 4,
  "radius": 300.0,
  "sofFactionName": "roguebase"
}