{
  "groupID": 1891,
  "iconID": 3626,
  "metaGroupID": 14,
  "name": {
    "de": "OLD Loki Electronics - Emergent Locus Analyzer Blueprint",
    "en": "OLD Loki Electronics - Emergent Locus Analyzer Blueprint",
    "es": "OLD Loki Electronics - Emergent Locus Analyzer Blueprint",
    "fr": "ANCIEN Plan de construction Loki Électronique – Analyseur de coordonnées émergent",
    "ja": "旧ロキエレクトロニクス - 緊急軌跡アナライザーブループリント",
    "ko": "OLD 로키 전자 시스템 - 위치 분석기 블루프린트",
    "ru": "OLD Loki Electronics - Emergent Locus Analyzer Blueprint",
    "zh": "旧洛基电子 - 出射光轨迹分析仪蓝图"
  },
  "portionSize": 1,
  "published": false,
  "volume": 0.01
}