{
  "typeID": 31707,
  "name": {
    "de": "Medium Projectile Metastasis Adjuster I Blueprint",
    "en": "Medium Projectile Metastasis Adjuster I Blueprint",
    "es": "Plano de ajustador metastásico de proyectiles mediano I",
    "fr": "Plan de construction Dispositif d'ajustage de métastase de projectiles intermédiaire I",
    "ja": "中型プロジェクタイルメタステイシスアジャスターIブループリント",
    "ko": "중형 발사체 메타스테이시스 I 블루프린트",
    "ru": "Medium Projectile Metastasis Adjuster I Blueprint",
    "zh": "中型射弹武器急转控制器蓝图 I"
  }
}