{
  "basePrice": 46320.0,
  "description": {
    "de": "Repariert im aktivierten Zustand Schäden an der Panzerung des Zielfahrzeugs.",
    "en": "Once activated, repairs damage done to the targeted vehicle's armor.",
    "es": "Una vez activado, repara el daño infligido al blindaje del vehículo objetivo.",
    "fr": "Après activation, répare les dommages occasionnés au blindage du véhicule ciblé.",
    "it": "Una volta attivato, ripara i danni inflitti alla corazza del veicolo colpito.",
    "ja": "一度起動すると、車両のアーマーが受けたダメージをリペアする。",
    "ko": "모듈 활성화 시 지정된 차량에 가해진 피해를 복구합니다.",
    "ru": "В активном состоянии осуществляет ремонт брони целевого транспортного средства.",
    "zh": "启用后，该装备会修复目标载具装甲的受损部位。"
  },
  "groupID": 351121,
  "name": {
    "de": "Schwerer polarisierter IG-R Fernregenerator für Panzerungen",
    "en": "Heavy Remote IG-R Polarized Armor Regenerator",
    "es": "Regenerador remoto de blindaje pesado polarizado IG-R",
    "fr": "Régénérateur de blindage à distance polarisé lourd IG-R",
    "it": "Rigeneratore corazza remoto pesante polarizzato IG-R",
    "ja": "ヘビー遠隔IG-Rポーラライズドアーマーリジェネレイター",
    "ko": "헤비 원격 IG-R 극성 장갑 재생장치",
    "ru": "Тяжелый дистанционный поляризационный регенератор брони IG-R",
    "zh": "重型远程IG-R极化装甲再生器"
  },
  "portionSize": 1,
  "published": false,
  "volume": 0.01
}