{
  "typeID": 354128,
  "name": {
    "de": "Leichter Clarity-Ward-Schildtransporter",
    "en": "Light Clarity Ward Shield Transporter",
    "es": "Transportador de escudo de protección ligero \"Clarity\"",
    "fr": "Transporteur de bouclier déflecteur léger Clarté",
    "it": "Trasportatore scudo difensivo leggero \"Clarity\"",
    "ja": "ライトクラリティウォードシールドトランスポーター",
    "ko": "라이트 차량 실드 트랜스포터",
    "ru": "Легкий модуль дистанционной накачки заградительного щита 'Clarity'",
    "zh": "轻型清澈防御护盾转移装置"
  }
}