{
  "description": {
    "de": "33,3% Bonus auf alle Schildresistenzen\n33,3% Reduktion des Signaturradius des Schiffs",
    "en": "33.3% bonus to all shield resistances\r\n33.3% reduction in ship signature radius",
    "es": "33,3 % de bonificación a todas las resistencias de escudo.\n\n33,3 % de reducción al radio de las señales de las naves.",
    "fr": "Bonus de résistances du blindage : +33 %\nBonus de rayon de signature du vaisseau : -33,3 %",
    "ja": "全てのシールドレジスタンスが33.3%増加。\r\n艦船のシグネチャ半径が33.3%縮小",
    "ko": "실드 저항력 33.3% 증가<br>함선 시그니처 반경 33.3% 감소",
    "ru": "на 33,3% повышается сопротивляемость силового поля корабля всем видам воздействия\nна 33,3% уменьшается размер сигнатуры корабля",
    "zh": "护盾抗性提高33.3%\n船只信号半径降低33.3%"
  },
  "groupID": 1306,
  "iconID": 1042,
  "mass": 100.0,
  "name": {
    "de": "Jackdaw-Verteidigungsmodus",
    "en": "Jackdaw Defense Mode",
    "es": "Modo de defensa de la Jackdaw",
    "fr": "Mode de Défense du Jackdaw",
    "ja": "ジャックドー防衛モード",
    "ko": "잭도우 방어 모드",
    "ru": "Jackdaw Defense Mode",
    "zh": "寒鸦级防御模式"
  },
  "portionSize": 1,
  "published": false,
  "raceID": 4,
  "radius": 50.0,
  "volume": 5.0
}