{
  "capacity": 1.0,
  "groupID": 1717,
  "iconID": 74,
  "mass": 500.0,
  "metaGroupID": 54,
  "name": {
    "de": "Structure Remote Sensor Booster",
    "en": "Structure Remote Sensor Booster",
    "es": "Potenciador de sensor remoto de estructura",
    "fr": "Amplificateur de détection à distance (Structure)",
    "ja": "ストラクチャ ― リモートセンサーブースター",
    "ko": "구조물 원격 센서 부스터",
    "ru": "Structure Remote Sensor Booster",
    "zh": "建筑远程感应增强器"
  },
  "portionSize": 1,
  "published": false,
  "volume": 4000.0
}