{
  "groupID": 1952,
  "name": {
    "de": "Kronos Intaki Syndicate Serenity Only SKIN (7 Days)",
    "en": "Kronos Intaki Syndicate Serenity Only SKIN (7 Days)",
    "es": "Kronos Intaki Syndicate Serenity Only SKIN (7 Days)",
    "fr": "Kronos Intaki Syndicate Serenity Only SKIN (7 Days)",
    "ja": "クロノス インタキシンジケート仕様セレニティー専用SKIN（7日）",
    "ko": "크로노스 '인타키 신디케이트' SKIN - 세레니티 전용 (7 일)",
    "ru": "Kronos Intaki Syndicate Serenity Only SKIN (7 Days)",
    "zh": "克洛诺斯级印塔基涂装（7天）"
  },
  "portionSize": 1,
  "published": false,
  "raceID": 8,
  "volume": 0.01
}