{
  "groupID": 1955,
  "name": {
    "de": "Nemesis Intaki Syndicate Serenity Only SKIN (365 Days)",
    "en": "Nemesis Intaki Syndicate Serenity Only SKIN (365 Days)",
    "es": "Nemesis Intaki Syndicate Serenity Only SKIN (365 Days)",
    "fr": "Nemesis Intaki Syndicate Serenity Only SKIN (365 Days)",
    "ja": "ネメシス インタキシンジケート仕様セレニティー専用SKIN（365日）",
    "ko": "네메시스 '인타키 신디케이트' SKIN - 세레니티 전용 (365 일)",
    "ru": "Nemesis Intaki Syndicate Serenity Only SKIN (365 Days)",
    "zh": "纳美西斯级印塔基涂装（365天）"
  },
  "portionSize": 1,
  "published": false,
  "raceID": 8,
  "volume": 0.01
}