{
  "groupID": 1953,
  "name": {
    "de": "Revelation EoM Serenity Only SKIN (30 Days)",
    "en": "Revelation EoM Serenity Only SKIN (30 Days)",
    "es": "Revelation EoM Serenity Only SKIN (30 Days)",
    "fr": "Revelation EoM Serenity Only SKIN (30 Days)",
    "ja": "レベレーション EoM仕様セレニティー専用SKIN（30日）",
    "ko": "레벨레이션 'EoM' SKIN - 세레니티 전용 (30 일)",
    "ru": "Revelation EoM Serenity Only SKIN (30 Days)",
    "zh": "神示级EoM涂装（30天）"
  },
  "portionSize": 1,
  "published": false,
  "raceID": 4,
  "volume": 0.01
}