{
  "typeID": 40454,
  "name": {
    "de": "Barghest Waschi Uprising 'Parade' Serenity Only SKIN (90 Days)",
    "en": "Barghest Waschi Uprising 'Parade' Serenity Only SKIN (90 Days)",
    "es": "Barghest Waschi Uprising 'Parade' Serenity Only SKIN (90 Days)",
    "fr": "Barghest Waschi Uprising 'Parade' Serenity Only SKIN (90 Days)",
    "ja": "バーゲスト ワチ・アップライジング「パレード」セレニティー専用SKIN（90日）",
    "ko": "바르게스트 '와스키 폭동 - 퍼레이드' SKIN - 세레니티 전용 (90 일)",
    "ru": "Barghest Waschi Uprising 'Parade' Serenity Only SKIN (90 Days)",
    "zh": "巴盖斯级瓦斯奇起义‘阅兵’涂装（90天）"
  },
  "volume": 0.01
}