{
  "capacity": 2700.0,
  "description": {
    "de": "Ein Serpentis-Forschungswarenlager Die Beseitigung der Wachen sollte bei der Überbrückung der Sicherheitsvorkehrungen behilflich sein.",
    "en": "A Serpentis research warehouse. Destroying its guards should help with bypassing its security.",
    "es": "Un almacén de investigación serpentis. Destruir a los guardias debería de bastar para burlar su seguridad.",
    "fr": "Un entrepôt de recherche serpentis. En détruisant ses gardes, il devrait être plus simple d'outrepasser son système de sécurité.",
    "ja": "サーペンティスの研究資材倉庫。警護要因を破壊すればセキュリティをかい潜れるだろう。",
    "ko": "서펜티스가 연구를 위해 사용하는 창고입니다. 경비함을 파괴하면 진입이 더욱 수월해질 것입니다.",
    "ru": "Склад лаборатории «змей». Уничтожение охраны поможет обойти системы безопасности.",
    "zh": "一座天蛇研究仓库。消灭它的守卫可以绕过它的安全系统。"
  },
  "graphicID": 2431,
  "groupID": 306,
  "mass": 10000.0,
  "name": {
    "de": "Research Warehouse",
    "en": "Research Warehouse",
    "es": "Almacén de investigación",
    "fr": "Entrepôt de recherche",
    "ja": "リサーチウェアハウス",
    "ko": "연구창고",
    "ru": "Research Warehouse",
    "zh": "研究仓库"
  },
  "portionSize": 1,
  "published": false,
  "radius": 75.0,
  "sofFactionName": "angelbase",
  "volume": 27500.0
}