{
  "description": {
    "de": "Ein Tresor im Besitz der Corporation Joint Harvesting.",
    "en": "A strong box belonging to the Joint Harvesting corporation.",
    "es": "Caja fuerte que pertenece a la corporación Joint Harvesting.",
    "fr": "Ce coffre-fort appartient à la corporation Joint Harvesting.",
    "ja": "共同採集コーポレーションの所有する金庫。",
    "ko": "조인트 하베스팅 코퍼레이션 소유의 금고입니다.",
    "ru": "Спецконтейнер корпорации «Совместная уборка урожая».",
    "zh": "属于联合收割集团的一个保险柜。"
  },
  "groupID": 1818,
  "iconID": 2039,
  "marketGroupID": 2317,
  "name": {
    "de": "Joint Harvesting Strong Box",
    "en": "Joint Harvesting Strong Box",
    "es": "Caja fuerte de Joint Harvesting",
    "fr": "Coffre-fort de Joint Harvesting",
    "ja": "共同採集金庫",
    "ko": "조인트 하베스팅 금고",
    "ru": "Joint Harvesting Strong Box",
    "zh": "联合收割保险柜"
  },
  "portionSize": 1,
  "published": true,
  "volume": 0.1
}