{
  "typeID": 44011,
  "name": {
    "de": "Standup M-Set Drone and Fighter Manufacturing Material Efficiency II Blueprint",
    "en": "Standup M-Set Drone and Fighter Manufacturing Material Efficiency II Blueprint",
    "es": "Plano de eficiencia de materiales en la fabricación de drones y cazas Standup II (M)",
    "fr": "Plan de construction Productivité matérielle de la production de drones et de chasseurs 'Standup' II M",
    "ja": "スタンドアップ中型ドローン・戦闘機製造資源効率II設計図",
    "ko": "스탠드업 M-Set 드론 및 파이터 제조 자원효율성 장치 II 블루프린트",
    "ru": "Standup M-Set Drone and Fighter Manufacturing Material Efficiency II Blueprint",
    "zh": "屹立中型无人机和铁骑舰载机制造材料效率蓝图 II"
  }
}