{
  "basePrice": 100000000.0,
  "groupID": 1708,
  "iconID": 21729,
  "metaGroupID": 53,
  "name": {
    "de": "Standup M-Set ME Research Accelerator II Blueprint",
    "en": "Standup M-Set ME Research Accelerator II Blueprint",
    "es": "Plano de aceleración de investigación de EM Standup mediana II",
    "fr": "Plan de construction Accélérateur de recherche en PM 'Standup' II M",
    "ja": "スタンドアップ中型ME研究加速器2のブループリント",
    "ko": "스탠드업 M-Set 자원효율성 연구 가속 장치 II 블루프린트",
    "ru": "Standup M-Set ME Research Accelerator II Blueprint",
    "zh": "屹立中型材料效率研究加速蓝图 II"
  },
  "portionSize": 1,
  "published": true,
  "volume": 0.01
}