{
  "typeID": 44615,
  "name": {
    "de": "Vengeance Ironblood Serenity Only SKIN (90 Days)",
    "en": "Vengeance Ironblood Serenity Only SKIN (90 Days)",
    "es": "Vengeance Ironblood Serenity Only SKIN (90 Days)",
    "fr": "SKIN Vengeance édition Ironblood, exclusivité Serenity (90 jours)",
    "ja": "ベンジェンス・アイアンブラッド・セレニティー専用SKIN（90日）",
    "ko": "벤젼스 '아이언블러드' SKIN - 세레니티 전용 (90 일)",
    "ru": "Vengeance Ironblood Serenity Only SKIN (90 Days)",
    "zh": "复仇级铁血涂装（90天）"
  },
  "volume": 0.01
}