{
  "typeID": 44753,
  "name": {
    "de": "Armageddon Ironblood Serenity Only SKIN (7 Days)",
    "en": "Armageddon Ironblood Serenity Only SKIN (7 Days)",
    "es": "Armageddon Ironblood Serenity Only SKIN (7 Days)",
    "fr": "SKIN Armageddon édition Ironblood, exclusivité Serenity (7 jours)",
    "ja": "アルマゲドン・アイアンブラッド・セレニティー専用SKIN（7日）",
    "ko": "아마겟돈 '아이언블러드' SKIN - 세레니티 전용 (7 일)",
    "ru": "Armageddon Ironblood Serenity Only SKIN (7 Days)",
    "zh": "末日沙场级铁血涂装（7天）"
  },
  "volume": 0.01
}