{
  "groupID": 973,
  "iconID": 3636,
  "metaGroupID": 14,
  "name": {
    "de": "Legion Core - Augmented Antimatter Reactor Blueprint",
    "en": "Legion Core - Augmented Antimatter Reactor Blueprint",
    "es": "Plano de núcleo de la Legion: reactor antimateria aumentado",
    "fr": "Plan de construction Legion Nucléus – Réacteur à antimatière augmenté",
    "ja": "レギオン・コア - オーグメンテッド・アンチマターリアクター設計図",
    "ko": "레기온 코어 시스템 - 강화 반물질 반응로 블루프린트",
    "ru": "Legion Core - Augmented Antimatter Reactor Blueprint",
    "zh": "圣卒核心 - 增强反物质反应堆蓝图"
  },
  "portionSize": 1,
  "published": true,
  "volume": 0.01
}