{
  "typeID": 46643,
  "name": {
    "de": "Standup M-Set Asteroid Ore Grading Processor I Blueprint",
    "en": "Standup M-Set Asteroid Ore Grading Processor I Blueprint",
    "es": "Plano de procesador de clasificación de mena asteroidal Standup I (M)",
    "fr": "Plan de construction Processeur de tri des minerais astéroïdaux Standup I M",
    "ja": "スタンドアップ中型アステロイド鉱石グレーディングプロセッサーI設計図",
    "ko": "스탠드업 M-Set 광물 품질관리 프로세서 I 블루프린트",
    "ru": "Standup M-Set Asteroid Ore Grading Processor I Blueprint",
    "zh": "屹立中型小行星矿石分级处理器蓝图 I"
  }
}