{
  "basePrice": 320000.0,
  "description": {
    "de": "Bedienung kleiner Precursor-Waffen. 5 % Bonus auf den Schaden von kleinen Precursor-Waffen je Skillstufe.",
    "en": "Operation of small precursor weapons. 5% Bonus to small precursor weapon damage per level.",
    "es": "Funcionamiento de armas precursoras pequeñas. 5 % de bonificación al daño de armas precursoras pequeñas por nivel.",
    "fr": "Aptitude à utiliser les petites armes de précursion. Augmente de 5 % par niveau les dégâts des petites armes de précursion.",
    "ja": "小型プリカーサー兵器の使用。レベルが上がるごとに小型プリカーサー兵器の与ダメージが5%増加。",
    "ko": "소형 프리커서 무기를 운용하기 위한 스킬입니다. 매 레벨마다 소형 프리커서 무기 피해량 5% 증가",
    "ru": "Использование малых орудий Предтечей. +5% к урону от малых орудий Предтечей за каждый уровень",
    "zh": "操作小型先驱者武器的技能。每升一级，小型先驱者武器的伤害提升5%。"
  },
  "groupID": 255,
  "iconID": 33,
  "marketGroupID": 364,
  "name": {
    "de": "Small Precursor Weapon",
    "en": "Small Precursor Weapon",
    "es": "Arma precursora pequeña",
    "fr": "Petite arme de précursion",
    "ja": "小型プリカーサー兵器",
    "ko": "소형 프리커서 무기",
    "ru": "Small Precursor Weapon",
    "zh": "小型先驱者武器研究"
  },
  "portionSize": 1,
  "published": true,
  "raceID": 135,
  "volume": 0.01
}