{
  "typeID": 49187,
  "name": {
    "de": "Covetor Amarr Industrial Livery Serenity Only SKIN (365 Days)",
    "en": "Covetor Amarr Industrial Livery Serenity Only SKIN (365 Days)",
    "es": "Covetor Amarr Industrial Livery Serenity Only SKIN (365 Days)",
    "fr": "Covetor Amarr Industrial Livery Serenity Only SKIN (365 Days)",
    "ja": "コベトアー・アマー輸送艦リベリー・セレニティー専用SKIN（365日）",
    "ko": "코베터 '아마르 인더스트리얼 리버리' SKIN - 세레니티 전용 (365 일)",
    "ru": "Covetor Amarr Industrial Livery Serenity Only SKIN (365 Days)",
    "zh": "妄想级艾玛工业制服涂装（365天）"
  }
}