{
  "typeID": 49217,
  "name": {
    "de": "Rorqual Amarr Industrial Livery Serenity Only SKIN (365 Days)",
    "en": "Rorqual Amarr Industrial Livery Serenity Only SKIN (365 Days)",
    "es": "Rorqual Amarr Industrial Livery Serenity Only SKIN (365 Days)",
    "fr": "Rorqual Amarr Industrial Livery Serenity Only SKIN (365 Days)",
    "ja": "ロークアル・アマー輸送艦リベリー・セレニティー専用SKIN（365日）",
    "ko": "로퀄 '아마르 인더스트리얼 리버리' SKIN - 세레니티 전용 (365 일)",
    "ru": "Rorqual Amarr Industrial Livery Serenity Only SKIN (365 Days)",
    "zh": "长须鲸级艾玛工业制服涂装（365天）"
  }
}