{
  "capacity": 235.0,
  "graphicID": 26204,
  "groupID": 1666,
  "mass": 10100000.0,
  "name": {
    "de": "Guristas Battlecruiser",
    "en": "Guristas Battlecruiser",
    "es": "Crucero de combate de los Guristas",
    "fr": "Croiseur cuirassé guristas",
    "ja": "ガリスタス巡洋戦艦",
    "ko": "구리스타스 배틀크루저",
    "ru": "Guristas Battlecruiser",
    "zh": "古斯塔斯战列巡洋舰"
  },
  "portionSize": 1,
  "published": false,
  "raceID": 1,
  "radius": 150.0,
  "sofFactionName": "guristas",
  "soundID": 20904,
  "volume": 101000.0
}