{
  "basePrice": 2000000.0,
  "capacity": 250.0,
  "graphicID": 21220,
  "groupID": 4034,
  "mass": 1630000.0,
  "metaGroupID": 2,
  "name": {
    "de": "Imperial Navy Deacon",
    "en": "Imperial Navy Deacon",
    "es": "Deacon de la Armada Imperial",
    "fr": "Deacon de la Navy impériale",
    "ja": "帝国海軍ディーコン",
    "ko": "제국 해군 디콘",
    "ru": "Imperial Navy Deacon",
    "zh": "帝国海军执事级"
  },
  "portionSize": 1,
  "published": false,
  "raceID": 4,
  "radius": 20.5,
  "sofFactionName": "carthum",
  "volume": 28700.0
}