{
  "basePrice": 17062768.0,
  "capacity": 515.0,
  "factionID": 500002,
  "graphicID": 1925,
  "groupID": 4034,
  "mass": 11000000.0,
  "metaGroupID": 2,
  "name": {
    "de": "Elite Republic Fleet Muninn",
    "en": "Elite Republic Fleet Muninn",
    "es": "Muninn de élite de la Flota de la República",
    "fr": "Muninn d'élite de la Republic Fleet",
    "ja": "エリート共和国海軍ムニン",
    "ko": "엘리트 공화국 함대 무닌",
    "ru": "Elite Republic Fleet Muninn",
    "zh": "精英共和舰队缪宁级"
  },
  "portionSize": 1,
  "published": false,
  "raceID": 2,
  "radius": 88.0,
  "sofFactionName": "boundlesscreation",
  "volume": 96000.0
}