{
  "capacity": 130.0,
  "graphicID": 3819,
  "groupID": 1568,
  "mass": 1500000.0,
  "name": {
    "de": "Guristas Automated VHF-08",
    "en": "Guristas Automated VHF-08",
    "es": "VHF-08 automatizada de los Guristas",
    "fr": "Guristas automatisé VHF-08",
    "ja": "ガリスタス・自動化VHF-08",
    "ko": "구리스타스 자동화 VHF-08",
    "ru": "Guristas Automated VHF-08",
    "zh": "古斯塔斯自动机械 VHF-08"
  },
  "portionSize": 1,
  "published": false,
  "raceID": 32,
  "radius": 35.0,
  "sofFactionName": "caldaribase",
  "soundID": 20102,
  "volume": 27289.0
}