{
  "typeID": 54541,
  "name": {
    "de": "Black Market 'Valdimar' Repair Drone Operation DR-903",
    "en": "Black Market 'Valdimar' Repair Drone Operation DR-903",
    "es": "Funcionamiento de drones reparadores Valdimar DR-903 del mercado negro",
    "fr": "Gestion de drones de réparation DR-903 « Valdimar » du marché noir",
    "ja": "ブラックマーケット「ヴァルディマー」リペアドローンオペレーションDR-903",
    "ko": "블랙 마켓 '발디마르' 수리 드론 운영 DR-903",
    "ru": "Black Market 'Valdimar' Repair Drone Operation DR-903",
    "zh": "黑市'弗拉基米尔'维修无人机操控 DR-903"
  },
  "volume": 1.0
}