{
  "description": {
    "de": "Enthält ein festliches Raketenwerfer-Modul sowie ein „Kaiserkrone“-Feuerwerksset",
    "en": "Contains a Festival Launcher module and a set of Crown Imperial fireworks",
    "es": "Contiene un módulo lanzador festivalero y un set de fuegos artificiales de la Corona del Imperio.",
    "fr": "Contient un module de lanceur de festival et des feux d'artifice de la couronne impériale",
    "ja": "フェスティバルランチャーモジュールとクラウンインペリアル花火のセットが入っている。",
    "ko": "축제용 런처 모듈과 크라운 임페리얼 폭죽이 포함되어 있습니다.",
    "ru": "Содержит модуль для праздничного запуска и набор фейерверков «Императорская корона»",
    "zh": "内含一个节日发射器和帝国皇冠焰火"
  },
  "groupID": 1194,
  "iconID": 24297,
  "name": {
    "de": "Amarr Foundation Day Fireworks Crate",
    "en": "Amarr Foundation Day Fireworks Crate",
    "es": "Caja con fuegos artificiales del Día de la Fundación de Amarr",
    "fr": "Caisse de feux d'artifice de la Journée de la fondation amarr",
    "ja": "アマー建国の日花火箱",
    "ko": "아마르 건국절 폭죽 상자",
    "ru": "Amarr Foundation Day Fireworks Crate",
    "zh": "艾玛国庆日焰火箱"
  },
  "portionSize": 1,
  "published": true,
  "volume": 0.1
}