{
  "description": {
    "de": "This crate is only designed for and available on Serenity.",
    "en": "This crate is only designed for and available on Serenity.",
    "es": "This crate is only designed for and available on Serenity.",
    "fr": "This crate is only designed for and available on Serenity.",
    "ja": "This crate is only designed for and available on Serenity.",
    "ko": "This crate is only designed for and available on Serenity.",
    "ru": "This crate is only designed for and available on Serenity.",
    "zh": "打开后可获得神秘奖品。\n\n奖品概率如下：\n\n小鬼级与长尾蜥级宝箱 57%\n变色龙级 36%\n恶魔级 7%"
  },
  "groupID": 314,
  "iconID": 24288,
  "mass": 1.0,
  "metaGroupID": 1,
  "name": {
    "de": "Serenity Ship Crate",
    "en": "Serenity Ship Crate",
    "es": "Serenity Ship Crate",
    "fr": "Serenity Ship Crate",
    "ja": "Serenity Ship Crate",
    "ko": "Serenity Ship Crate",
    "ru": "Serenity Ship Crate",
    "zh": "尊享稀有舰船宝箱"
  },
  "portionSize": 1,
  "published": true,
  "volume": 1.0
}