{
  "typeID": 64735,
  "name": {
    "de": "Federation Grand Prix History Route: Verge Vendor Colonies",
    "en": "Federation Grand Prix History Route: Verge Vendor Colonies",
    "es": "Ruta histórica del Gran Premio de la Federación: Colonias de Verge Vendor",
    "fr": "Itinéraire historique du Grand Prix de la Fédération : colonies de Verge Vendor",
    "ja": "連邦グランプリ歴史ルート: バージベンダーコロニー",
    "ko": "그랑프리 연방의 역사 코스: 버지 벤더 콜로니",
    "ru": "Federation Grand Prix History Route: Verge Vendor Colonies",
    "zh": "联邦大奖赛历史之旅：维格温铎殖民地"
  }
}