{
  "capacity": 10000.0,
  "graphicID": 2593,
  "groupID": 1975,
  "mass": 100000.0,
  "name": {
    "de": "Non-Interactable Amarr Starbase Control Tower (Do not translate)",
    "en": "Non-Interactable Amarr Starbase Control Tower (Do not translate)",
    "es": "Non-Interactable Amarr Starbase Control Tower (Do not translate)",
    "fr": "Non-Interactable Amarr Starbase Control Tower (Do not translate)",
    "ja": "Non-Interactable Amarr Starbase Control Tower (Do not translate)",
    "ko": "Non-Interactable Amarr Starbase Control Tower (Do not translate)",
    "ru": "Non-Interactable Amarr Starbase Control Tower (Do not translate)",
    "zh": "Non-Interactable Amarr Starbase Control Tower (Do not translate)"
  },
  "portionSize": 1,
  "published": false,
  "raceID": 4,
  "radius": 3394.0,
  "sofFactionName": "amarrbase",
  "volume": 100000000.0
}