{
  "typeID": 71057,
  "name": {
    "de": "Non-interactable Gallente Battery (do not translate)",
    "en": "Non-interactable Gallente Battery (do not translate)",
    "es": "Non-interactable Gallente Battery (do not translate)",
    "fr": "Non-interactable Gallente Battery (do not translate)",
    "ja": "Non-interactable Gallente Battery (do not translate)",
    "ko": "Non-interactable Gallente Battery (do not translate)",
    "ru": "Non-interactable Gallente Battery (do not translate)",
    "zh": "Non-interactable Gallente Battery (do not translate)"
  },
  "volume": null
}