{
  "graphicID": 22189,
  "groupID": 1924,
  "mass": 3000000000.0,
  "name": {
    "de": "Gallente Federation Stronghold",
    "en": "Gallente Federation Stronghold",
    "es": "Bastión de la Federación Gallente",
    "fr": "Forteresse de la Fédération gallente",
    "ja": "ガレンテ連邦の要塞",
    "ko": "갈란테 연방 요새",
    "ru": "Gallente Federation Stronghold",
    "zh": "盖伦特联邦要塞"
  },
  "portionSize": 1,
  "published": false,
  "raceID": 8,
  "radius": 50000.0,
  "sofFactionName": "gallentebase",
  "soundID": 20244,
  "volume": 8000.0
}