{
  "graphicID": 25315,
  "groupID": 1975,
  "name": {
    "de": "Guristas Outpost Wreckage ( Boombox DO NOT TRANSLATE)",
    "en": "Guristas Outpost Wreckage ( Boombox DO NOT TRANSLATE)",
    "es": "Guristas Outpost Wreckage ( Boombox DO NOT TRANSLATE)",
    "fr": "Guristas Outpost Wreckage ( Boombox DO NOT TRANSLATE)",
    "ja": "Guristas Outpost Wreckage ( Boombox DO NOT TRANSLATE)",
    "ko": "Guristas Outpost Wreckage ( Boombox DO NOT TRANSLATE)",
    "ru": "Guristas Outpost Wreckage ( Boombox DO NOT TRANSLATE)",
    "zh": "Guristas Outpost Wreckage ( Boombox DO NOT TRANSLATE)"
  },
  "portionSize": 1,
  "published": false,
  "radius": 22000.0,
  "sofFactionName": "guristas",
  "soundID": 20236
}