{
  "typeID": 80343,
  "name": {
    "de": "Expired Extended Capsuleer Day XXI Cerebral Accelerator",
    "en": "Expired Extended Capsuleer Day XXI Cerebral Accelerator",
    "es": "Acelerador cerebral ampliado del XXI Día de los Capsulistas caducado",
    "fr": "Accélérateur cérébral prolongé du Jour des Capsuliers XXI expiré",
    "ja": "期限切れ拡張カプセラデーXXI大脳アクセラレーター",
    "ko": "만료된 익스텐드 캡슐리어의 날 XXI 대뇌가속기",
    "ru": "Expired Extended Capsuleer Day XXI Cerebral Accelerator",
    "zh": "过期的延展型克隆飞行员之日XXI大脑加速器"
  }
}