{
  "activities": {
    "copying": {
      "materials": [
        {
          "quantity": 1,
          "typeID": 11458
        },
        {
          "quantity": 55,
          "typeID": 3812
        }
      ],
      "skills": [
        {
          "level": 3,
          "typeID": 11433
        },
        {
          "level": 3,
          "typeID": 11455
        }
      ],
      "time": 2160
    },
    "manufacturing": {
      "materials": [
        {
          "quantity": 138,
          "typeID": 40
        },
        {
          "quantity": 12169,
          "typeID": 34
        },
        {
          "quantity": 6778,
          "typeID": 35
        },
        {
          "quantity": 1099,
          "typeID": 36
        },
        {
          "quantity": 3276,
          "typeID": 37
        }
      ],
      "products": [
        {
          "quantity": 1,
          "typeID": 15885
        }
      ],
      "skills": [
        {
          "level": 1,
          "typeID": 3380
        }
      ],
      "time": 2700
    },
    "research_material": {
      "time": 945
    },
    "research_time": {
      "time": 945
    }
  }
}