{
  "activities": {
    "copying": {
      "time": 2160
    },
    "manufacturing": {
      "materials": [
        {
          "quantity": 22,
          "typeID": 40
        },
        {
          "quantity": 122,
          "typeID": 34
        },
        {
          "quantity": 1342,
          "typeID": 35
        },
        {
          "quantity": 9,
          "typeID": 38
        },
        {
          "quantity": 4,
          "typeID": 39
        }
      ],
      "products": [
        {
          "quantity": 1,
          "typeID": 17485
        }
      ],
      "skills": [
        {
          "level": 1,
          "typeID": 3380
        }
      ],
      "time": 2700
    },
    "research_material": {
      "time": 945
    },
    "research_time": {
      "time": 945
    }
  },
  "blueprintTypeID": 17486,
  "maxProductionLimit": 60
}