{
  "activities": {
    "copying": {
      "time": 720
    },
    "manufacturing": {
      "materials": [
        {
          "quantity": 1,
          "typeID": 23168
        },
        {
          "quantity": 1,
          "typeID": 23169
        },
        {
          "quantity": 2,
          "typeID": 23138
        },
        {
          "quantity": 658,
          "typeID": 35
        },
        {
          "quantity": 2,
          "typeID": 36
        },
        {
          "quantity": 4,
          "typeID": 37
        },
        {
          "quantity": 1,
          "typeID": 38
        },
        {
          "quantity": 4,
          "typeID": 39
        },
        {
          "quantity": 3,
          "typeID": 23139
        },
        {
          "quantity": 1,
          "typeID": 23128
        },
        {
          "quantity": 2,
          "typeID": 23129
        }
      ],
      "products": [
        {
          "quantity": 1,
          "typeID": 22953
        }
      ],
      "skills": [
        {
          "level": 5,
          "typeID": 3380
        },
        {
          "level": 2,
          "typeID": 23124
        }
      ],
      "time": 900
    },
    "research_material": {
      "time": 315
    },
    "research_time": {
      "time": 315
    }
  },
  "blueprintTypeID": 22954,
  "maxProductionLimit": 200
}