{
  "activities": {
    "reaction": {
      "materials": [
        {
          "quantity": 5,
          "typeID": 4247
        },
        {
          "quantity": 12,
          "typeID": 25339
        },
        {
          "quantity": 15,
          "typeID": 25237
        },
        {
          "quantity": 20,
          "typeID": 3773
        }
      ],
      "products": [
        {
          "quantity": 12,
          "typeID": 25346
        }
      ],
      "skills": [
        {
          "level": 4,
          "typeID": 45746
        }
      ],
      "time": 10800
    }
  }
}