{
  "activities": {
    "manufacturing": {
      "materials": [
        {
          "quantity": 46,
          "typeID": 52314
        },
        {
          "quantity": 52,
          "typeID": 11399
        },
        {
          "quantity": 132,
          "typeID": 52313
        },
        {
          "quantity": 355,
          "typeID": 2346
        },
        {
          "quantity": 388,
          "typeID": 2367
        }
      ],
      "products": [
        {
          "quantity": 1,
          "typeID": 52790
        }
      ],
      "skills": [
        {
          "level": 4,
          "typeID": 3380
        }
      ],
      "time": 9000
    }
  },
  "blueprintTypeID": 52796,
  "maxProductionLimit": 30
}