{
  "activities": {
    "reaction": {
      "materials": [
        {
          "quantity": 5,
          "typeID": 4312
        },
        {
          "quantity": 100,
          "typeID": 16634
        },
        {
          "quantity": 100,
          "typeID": 16636
        }
      ],
      "products": [
        {
          "quantity": 200,
          "typeID": 57455
        }
      ],
      "skills": [
        {
          "level": 1,
          "typeID": 45746
        }
      ],
      "time": 10800
    }
  },
  "blueprintTypeID": 57494,
  "maxProductionLimit": 1000
}